{"info": {"dt": 10, "num_train_routines": 50, "num_test_routines": 10, "start_time": 360, "end_time": 1440, "only_used_objects": true, "idle_sampling_factor": 1.0, "block_activity_for_hrs": 3, "min_ideal_transition_prec": 0.5, "num_nodes": 67, "search_object_ids": [1014, 1015, 1028, 1029, 1032, 1035, 1039, 1047, 1053, 1054, 1058, 1067, 1069, 1076, 1107, 1113, 1119, 1120, 1121, 1132, 1133, 1137, 1140, 1146, 1149, 1151, 1154, 1160, 1165, 1174, 1181, 1185, 1189, 1191, 1201, 1202, 1204, 1205, 1208, 1215], "search_object_names": ["bag", "basket_for_clothes", "cd", "cd_player", "chessboard", "cloth_napkin", "clothes_jacket", "coffee_cup", "conditioner", "cookingpot", "deck_of_cards", "drinking_glass", "drying_rack", "facial_cleanser", "food_rice", "food_vegetable", "hairbrush", "hairdryer", "headset", "keyboard", "keys", "laundry_detergent", "mail", "mug", "napkin", "note_pad", "oil", "pen", "plate", "remote_control", "shampoo", "shoes", "spectacles", "spoon", "tooth_paste", "toothbrush", "towel", "towel_rack", "vacuum_cleaner", "wine_glass"]}, "node_ids": [1, 16, 17, 18, 41, 99, 102, 113, 114, 117, 119, 120, 129, 162, 241, 269, 270, 272, 273, 275, 999, 1000, 1002, 1004, 1006, 1008, 1010, 1014, 1015, 1028, 1029, 1032, 1035, 1047, 1053, 1054, 1058, 1067, 1069, 1076, 1107, 1113, 1119, 1120, 1121, 1132, 1133, 1137, 1140, 1146, 1149, 1151, 1154, 1160, 1165, 1174, 1181, 1185, 1189, 1191, 1201, 1202, 1204, 1205, 1208, 1215], "node_classes": ["bathroom", "shower", "bathroom_cabinet", "bathroom_counter", "dining_room", "trashcan", "mat", "bench", "table", "cupboard", "kitchen_counter", "sink", "dishwasher", "bedroom", "home_office", "sofa", "table", "desk", "tvstand", "bookshelf", "outside", "washing_machine", "stove", "kitchen_cabinet", "fridge", "dresser", "shoe_rack", "bag", "basket_for_clothes", "cd", "cd_player", "chessboard", "cloth_napkin", "coffee_cup", "conditioner", "cookingpot", "deck_of_cards", "drinking_glass", "drying_rack", "facial_cleanser", "food_rice", "food_vegetable", "hairbrush", "hairdryer", "headset", "keyboard", "keys", "laundry_detergent", "mail", "mug", "napkin", "note_pad", "oil", "pen", "plate", "remote_control", "shampoo", "shoes", "spectacles", "spoon", "tooth_paste", "toothbrush", "towel", "towel_rack", "vacuum_cleaner", "wine_glass"], "node_categories": ["Rooms", "Furniture", "Furniture", "Furniture", "Rooms", "Props", "Decor", "Furniture", "Furniture", "Furniture", "Furniture", "Furniture", "Appliances", "Rooms", "Rooms", "Furniture", "Furniture", "Furniture", "Furniture", "Furniture", "Rooms", "Appliances", "Appliances", "Furniture", "Appliances", "Furniture", "Furniture", "placable_objects", "placable_objects", "placable_objects", "placable_objects", "placable_objects", "placable_objects", "placable_objects", "placable_objects", "placable_objects", "placable_objects", "placable_objects", "placable_objects", "placable_objects", "placable_objects", "placable_objects", "placable_objects", "placable_objects", "placable_objects", "placable_objects", "placable_objects", "placable_objects", "placable_objects", "placable_objects", "placable_objects", "placable_objects", "placable_objects", "placable_objects", "placable_objects", "placable_objects", "placable_objects", "placable_objects", "placable_objects", "placable_objects", "placable_objects", "placable_objects", "placable_objects", "placable_objects", "placable_objects", "placable_objects"], "node_idx_from_id": {"1": 0, "16": 1, "17": 2, "18": 3, "41": 4, "99": 5, "102": 6, "113": 7, "114": 8, "117": 9, "119": 10, "120": 11, "129": 12, "162": 13, "241": 14, "269": 15, "270": 16, "272": 17, "273": 18, "275": 19, "999": 20, "1000": 21, "1002": 22, "1004": 23, "1006": 24, "1008": 25, "1010": 26, "1014": 27, "1015": 28, "1028": 29, "1029": 30, "1032": 31, "1035": 32, "1047": 33, "1053": 34, "1054": 35, "1058": 36, "1067": 37, "1069": 38, "1076": 39, "1107": 40, "1113": 41, "1119": 42, "1120": 43, "1121": 44, "1132": 45, "1133": 46, "1137": 47, "1140": 48, "1146": 49, "1149": 50, "1151": 51, "1154": 52, "1160": 53, "1165": 54, "1174": 55, "1181": 56, "1185": 57, "1189": 58, "1191": 59, "1201": 60, "1202": 61, "1204": 62, "1205": 63, "1208": 64, "1215": 65}, "activities": ["brushing_teeth", "showering", "breakfast", "dinner", "computer_work", "lunch", "cleaning", "laundry", "leave_home", "come_home", "socializing", "taking_medication", "watching_tv", "vaccuum_cleaning", "reading", "going_to_the_bathroom", "getting_dressed", "kitchen_cleaning", "take_out_trash", "wash_dishes", "playing_music", "listening_to_music", null], "actions": [], "edge_keys": ["INSIDE", "ON"], "static_nodes": [16, 17, 18, 113, 114, 117, 119, 120, 269, 270, 272, 273, 275, 1004, 1008, 1010], "train_data_index_list": [["044", 105], ["045", 116], ["030", 120], ["043", 105], ["046", 102], ["020", 110], ["035", 117], ["003", 104], ["048", 101], ["017", 127], ["037", 110], ["036", 124], ["006", 105], ["034", 104], ["011", 122], ["041", 114], ["025", 108], ["039", 108], ["049", 110], ["015", 109], ["007", 122], ["004", 101], ["040", 105], ["022", 108], ["018", 110], ["032", 132], ["028", 110], ["016", 116], ["027", 116], ["024", 111], ["019", 109], ["000", 107], ["047", 132], ["001", 109], ["026", 106], ["033", 100], ["038", 119], ["029", 91], ["012", 109], ["014", 109], ["010", 100], ["042", 123], ["031", 104], ["009", 110], ["002", 110], ["008", 92], ["021", 105], ["005", 122], ["023", 134], ["013", 109]], "test_data_index_list": [["003", 110], ["006", 111], ["007", 114], ["004", 111], ["000", 100], ["001", 101], ["009", 102], ["002", 106], ["008", 117], ["005", 100]]}